LICENSE
MANIFEST.in
README.md
requirements.txt
setup.py
./scissors/search.cpp
intelligent_scissors.egg-info/PKG-INFO
intelligent_scissors.egg-info/SOURCES.txt
intelligent_scissors.egg-info/dependency_links.txt
intelligent_scissors.egg-info/requires.txt
intelligent_scissors.egg-info/top_level.txt
scissors/__init__.py
scissors/feature_extraction.py
scissors/gui.py
scissors/search.cpp
scissors/search.pyx
scissors/setup.py
scissors/utils.py