Metadata-Version: 2.1
Name: intelligent-scissors
Version: 2.0
Summary: Intelligent Scissors tool
Home-page: https://github.com/stanislaushimovolos/Intelligent-Scissors
Author: Stanislav Shimovolos
Author-email: shimovolos.sa@phystech.edu
License: MIT
Download-URL: https://github.com/stanislaushimovolos/Intelligent-Scissors/v2.0.tar.gz
Platform: UNKNOWN
Classifier: Programming Language :: Python :: 3
Classifier: License :: OSI Approved :: MIT License
Classifier: Operating System :: OS Independent
Requires-Python: >=3.5
